Metadata-Version: 2.1
Name: predictasearch
Version: 1.0.0
Summary: Python library and command-line utility for Predicta Search API
Home-page: https://github.com/predictalab/predictasearch-python
Author: Predicta Lab
Author-email: contact@predictalab.com
Project-URL: Homepage, https://github.com/predictalab/predictasearch-python
Project-URL: Repository, https://github.com/predictalab/predictasearch-python
Project-URL: Issues, https://github.com/predictalab/predictasearch-python/issues
Classifier: Programming Language :: Python :: 3.8
Classifier: Programming Language :: Python :: 3.9
Classifier: Programming Language :: Python :: 3.10
Classifier: Programming Language :: Python :: 3.11
Classifier: Programming Language :: Python :: 3.12
Classifier: Programming Language :: Python :: 3.13
Classifier: Programming Language :: Python :: 3.14
Classifier: License :: OSI Approved :: MIT License
Classifier: Operating System :: OS Independent
Classifier: Natural Language :: English
Classifier: Topic :: Software Development :: Libraries :: Python Modules
Classifier: Intended Audience :: Developers
Classifier: Development Status :: 5 - Production/Stable
Requires-Python: >=3.8
License-File: LICENSE
Requires-Dist: requests>=2.32.3
